alu4.v
module alu4 (
input [3:0] A,
input [3:0] B,
input Cin, // Carry in
input [1:0] Operation, // Operation Select (S1, S0)
input Mode, // Mode Select (M)
output [3:0] F, // Result
output Cout // Carry out
);
reg [3:0] result;
reg carry_out;
always @(*) begin // Combinational logic
case (Mode)
1'b0: begin // Logic operations
case (Operation)
2'b00: result = A & B; // AND
2'b01: result = A | B; // OR
2'b10: result = A ^ B; // XOR
2'b11: result = (A ^ B); // XNOR
endcase
carry_out = 1'b0; // No carry out for logic operations
end
1'b1: begin // Arithmetic operations
case ({Operation, Cin})
3'b000: result = A; // Transfer A
3'b001: {carry_out, result} = A + 1'b1; // Increment A by 1
3'b010: {carry_out, result} = A + B; // Add A and B
3'b011: {carry_out, result} = A + B + 1'b1; // Increment sum of A and B by 1
3'b100: {carry_out, result} = A + (~B); // A plus one's complement of B
3'b101: {carry_out, result} = A + (~B); // Subtract B from A (A - B)
3'b110: {carry_out, result} = (A) + B; // B plus one's complement of A
3'b111: {carry_out, result} = (A) + B + 1'b1; // B minus A (B - A)
endcase
end
endcase
end
assign F = result;
assign Cout = carry_out;
endmodule

alu4_tb.v
`include "alu4.v"

module alu4_tb;
// Inputs
reg [3:0] A;
reg [3:0] B;
reg Cin;
reg [1:0] Operation;
reg Mode;
// Outputs
wire [3:0] F;
wire Cout;
// Instantiate the ALU module
alu4 auut (
.A(A),
.B(B),
.Cin(Cin),
.Operation(Operation),
.Mode(Mode),
.F(F),
.Cout(Cout)
);
initial begin

    $dumpfile("alu4.vcd");
    $dumpvars(0,alu4_tb);
// Initialize inputs
A = 4'b0000;
B = 4'b0000;
Cin = 1'b0;
Mode = 1'b0; // Start with Logic Mode
Operation = 2'b00;
// Test cases for Logic Mode (M = 0)
$monitor("Time=%0t, Mode=%b, Op=%b, A=%b, B=%b, F=%b",
$time, Mode, Operation, A, B, F);

#10 Operation = 2'b01;
#10 Operation = 2'b10;
#10 Operation = 2'b11;
#10 A = 4'b0101;
#10 B = 4'b1010;
#10 Operation = 2'b00;
#10 Operation = 2'b01;
#10 Operation = 2'b10;
#10 Operation = 2'b11;
// Switch to Arithmetic Mode (M = 1)
#10 Mode = 1'b1;
A = 4'b0000;
B = 4'b0000;
Cin = 1'b0;
Operation = 2'b00;

// Test cases for Arithmetic Mode (M = 1)
$monitor("Time=%0t, Mode=%b, Op=%b, Cin=%b, A=%b, B=%b, F=%b, Cout=%b",
    $time, Mode, Operation, Cin, A, B, F, Cout);

#10 Operation = 2'b01;
#10 Operation = 2'b10;
#10 Operation = 2'b11;
#10 A = 4'b0101;
#10 B = 4'b1010;
#10 Operation = 2'b00;
#10 Operation = 2'b01;
#10 Operation = 2'b10;
#10 Operation = 2'b11;
#10 Cin = 1'b1;
#10 Operation = 2'b00;
#10 Operation = 2'b01;
#10 Operation = 2'b10;
#10 Operation = 2'b11;
#10 $finish;
end
endmodule

alu4.vcd
$date
	Wed Oct 23 17:09:14 2024
$end
$version
	Icarus Verilog
$end
$timescale
	1s
$end
$scope module alu4_tb $end
$var wire 4 ! F [3:0] $end
$var wire 1 " Cout $end
$var reg 4 # A [3:0] $end
$var reg 4 $ B [3:0] $end
$var reg 1 % Cin $end
$var reg 1 & Mode $end
$var reg 2 ' Operation [1:0] $end
$scope module auut $end
$var wire 4 ( A [3:0] $end
$var wire 4 ) B [3:0] $end
$var wire 1 % Cin $end
$var wire 1 " Cout $end
$var wire 4 * F [3:0] $end
$var wire 1 & Mode $end
$var wire 2 + Operation [1:0] $end
$var reg 1 , carry_out $end
$var reg 4 - result [3:0] $end
$upscope $end
$upscope $end
$enddefinitions $end
$comment Show the parameter values. $end
$dumpall
$end
#0
$dumpvars
b0 -
0,
b0 +
b0 *
b0 )
b0 (
b0 '
0&
0%
b0 $
b0 #
0"
b0 !
$end
#10
b1 '
b1 +
#20
b10 '
b10 +
#30
b11 '
b11 +
#40
b101 !
b101 *
b101 -
b101 #
b101 (
#50
b1111 !
b1111 *
b1111 -
b1010 $
b1010 )
#60
b0 !
b0 *
b0 -
b0 '
b0 +
#70
b1111 !
b1111 *
b1111 -
b1 '
b1 +
#80
b10 '
b10 +
#90
b11 '
b11 +
#100
b0 !
b0 *
b0 -
b0 '
b0 +
b0 $
b0 )
b0 #
b0 (
1&
#110
b1 '
b1 +
#120
1"
1,
b1111 !
b1111 *
b1111 -
b10 '
b10 +
#130
0"
0,
b0 !
b0 *
b0 -
b11 '
b11 +
#140
b101 !
b101 *
b101 -
b101 #
b101 (
#150
b1111 !
b1111 *
b1111 -
b1010 $
b1010 )
#160
b101 !
b101 *
b101 -
b0 '
b0 +
#170
b1111 !
b1111 *
b1111 -
b1 '
b1 +
#180
1"
1,
b1010 !
b1010 *
b1010 -
b10 '
b10 +
#190
0"
0,
b1111 !
b1111 *
b1111 -
b11 '
b11 +
#200
1"
1,
b0 !
b0 *
b0 -
1%
#210
0"
0,
b110 !
b110 *
b110 -
b0 '
b0 +
#220
1"
1,
b0 !
b0 *
b0 -
b1 '
b1 +
#230
b1010 !
b1010 *
b1010 -
b10 '
b10 +
#240
b0 !
b0 *
b0 -
b11 '
b11 +
