andGate.v
module andGate(a,b,c);
    input a;
    input b;
    output c;

    assign c = a & b;

endmodule

xorGate_df.v
module xorGate_df(input a,b, output c);
    assign c = a ^ b; // xor operator
endmodule

full_adder_st.v
`include "xorGate_df.v"
`include "andGate.v"

module full_adder_st(output sum, carry, input a,b,c);
    wire xorOut1, xorOut2, xorOut3;
    wire andOut1, andOut2;

    // instantiate xor gates
    xorGate_df xorA(a,b,xorOut1);
    xorGate_df xorB(xorOut1,c,sum); //sum
    xorGate_df xorC(andOut1,andOut2,carry); //carry

    // instantiate and gates
    andGate andA(xorOut1,c,andOut1);
    andGate andB(a,b,andOut2);

endmodule

full_adder_bh.v
module full_adder_bh(output reg sum,carry, input a,b,c);
    always @(*) begin
        sum = a ^ b ^ c;
        carry = (((a ^ b)&c) ^ (a&b));
    end 
endmodule

full_adder_df.v
module full_adder_df(output sum, carry, input a,b,c);
    assign sum = (a ^ b) ^ c;
    assign carry = (((a ^ b)&c) ^ (a&b));
endmodule

full_adder_tb.v
`include "full_adder_df.v"
`include "full_adder_bh.v"
`include "full_adder_st.v"
module full_adder_tb;
    reg a, b, c;  // Inputs
    wire sum_df, carry_df;  // Outputs for dataflow full adder
    wire sum_bh, carry_bh;  // Outputs for behavioral full adder
    wire sum_st, carry_st;  // Outputs for structural full adder
    initial begin
        $dumpfile("full_adder.vcd");
        $dumpvars(0, full_adder_tb);
        $monitor("a=%b, b=%b, c=%b | sum_df=%b, carry_df=%b | sum_bh=%b, carry_bh=%b | sum_st=%b, carry_st=%b", 
                a, b, c, sum_df, carry_df, sum_bh, carry_bh, sum_st, carry_st);
        // Test different input combinations
        a = 0; b = 0; c = 0;
        #5 a = 0; b = 0; c = 1;
        #5 a = 0; b = 1; c = 0;
        #5 a = 0; b = 1; c = 1;
        #5 a = 1; b = 0; c = 0;
        #5 a = 1; b = 0; c = 1;
        #5 a = 1; b = 1; c = 0;
        #5 a = 1; b = 1; c = 1;
        #5 $finish;
    end
    full_adder_df fullAdder1( // Instantiate full_adder_df (dataflow)
        .sum(sum_df),
        .carry(carry_df),
        .a(a),
        .b(b),
        .c(c)
    );
    full_adder_bh fullAdder2( // Instantiate full_adder_bh (behavioral)
        .sum(sum_bh),
        .carry(carry_bh),
        .a(a),
        .b(b),
        .c(c)
    );
    full_adder_st fullAdder3( // Instantiate full_adder_st (structural)
        .sum(sum_st),
        .carry(carry_st),
        .a(a),
        .b(b),
        .c(c)
    );
endmodule

full_adder.vcd
$date
	Mon Sep 23 15:21:14 2024
$end
$version
	Icarus Verilog
$end
$timescale
	1s
$end
$scope module full_adder_tb $end
$var wire 1 ! sum_st $end
$var wire 1 " sum_df $end
$var wire 1 # sum_bh $end
$var wire 1 $ carry_st $end
$var wire 1 % carry_df $end
$var wire 1 & carry_bh $end
$var reg 1 ' a $end
$var reg 1 ( b $end
$var reg 1 ) c $end
$scope module fullAdder1 $end
$var wire 1 ' a $end
$var wire 1 ( b $end
$var wire 1 ) c $end
$var wire 1 % carry $end
$var wire 1 " sum $end
$upscope $end
$scope module fullAdder2 $end
$var wire 1 ' a $end
$var wire 1 ( b $end
$var wire 1 ) c $end
$var reg 1 & carry $end
$var reg 1 # sum $end
$upscope $end
$scope module fullAdder3 $end
$var wire 1 ' a $end
$var wire 1 ( b $end
$var wire 1 ) c $end
$var wire 1 * xorOut1 $end
$var wire 1 ! sum $end
$var wire 1 $ carry $end
$var wire 1 + andOut2 $end
$var wire 1 , andOut1 $end
$scope module andA $end
$var wire 1 ) b $end
$var wire 1 , c $end
$var wire 1 * a $end
$upscope $end
$scope module andB $end
$var wire 1 ' a $end
$var wire 1 ( b $end
$var wire 1 + c $end
$upscope $end
$scope module xorA $end
$var wire 1 ' a $end
$var wire 1 ( b $end
$var wire 1 * c $end
$upscope $end
$scope module xorB $end
$var wire 1 * a $end
$var wire 1 ) b $end
$var wire 1 ! c $end
$upscope $end
$scope module xorC $end
$var wire 1 , a $end
$var wire 1 + b $end
$var wire 1 $ c $end
$upscope $end
$upscope $end
$upscope $end
$enddefinitions $end
$comment Show the parameter values. $end
$dumpall
$end
#0
$dumpvars
0,
0+
0*
0)
0(
0'
0&
0%
0$
0#
0"
0!
$end
#5
1"
1#
1!
1)
#10
1*
0)
1(
#15
1%
1$
0"
1&
0#
1,
0!
1)
#20
0%
0$
1"
0,
1!
0&
1#
0)
0(
1'
#25
1%
1$
0"
1&
0#
1,
0!
1)
#30
0,
1+
0*
0)
1(
#35
1"
1#
1!
1)
