orGate_df.v
//Dataflow style
module orGate_df(input a, b, output c);
    assign c = a | b;
endmodule

andGate.v
module andGate(a,b,c);
    input a;
    input b;
    output c;

    assign c = a & b;

endmodule

notGate_df.v
module notGate_df(input a, output b);
    assign b = ~a;
endmodule

mux8x1_st.v
`include "andGate.v" // (input a,b, output y)
`include "orGate_df.v" // (input a,b, output y)
`include "notGate_df.v" // (input a, output y)

module mux8x1_st(
    input I0, I1, I2, I3, I4, I5, I6, I7, // Inputs
    input S0, S1, S2,                     // Select lines
    output Y                              // Output
);

    wire S0n, S1n, S2n; // Inverted select lines
    wire D0, D1, D2, D3, D4, D5, D6, D7; // AND gate outputs
    // inner AND gate outputs
    wire E1,E2; 
    wire E3,E4; 
    wire E5,E6;
    wire E7,E8;
    wire E9,E10;
    wire E11,E12;
    wire E13,E14;
    wire E15,E16; 
    
    // Invert the select lines using notGate_df
    notGate_df not0(S0, S0n); // S0 not
    notGate_df not1(S1, S1n); // S1 not
    notGate_df not2(S2, S2n); // S2 not

    //for D0 AND gate (S2n, S1n, S0n)
    andGate and1(S2n, S1n, E1);
    andGate and2(S0n, I0, E2);
    andGate and_D0(E1, E2, D0); // D0 output

    //for D1 AND gate (S2n, S1n, S0)
    andGate and3(S2n, S1n, E3);
    andGate and4(S0, I1, E4);
    andGate and_D1(E3, E4, D1); // D1 output

    //for D2 AND gate (S2n, S1, S0n)
    andGate and5(S2n, S1, E5);
    andGate and6(S0n, I2, E6);
    andGate and_D2(E5, E6, D2); // D2 output

    //for D3 AND gate (S2n, S1, S0)
    andGate and7(S2n, S1, E7);
    andGate and8(S0, I3, E8);
    andGate and_D3(E7, E8, D3); // D3 output

    //for D4 AND gate (S2, S1n, S0n)
    andGate and9(S2, S1n, E9);
    andGate and10(S0n, I4, E10);
    andGate and_D4(E9, E10, D4); // D4 output
    
    //for D5 AND gate (S2, S1n, S0)
    andGate and11(S2, S1n, E11);
    andGate and12(S0, I5, E12);
    andGate and_D5(E11, E12, D5); // D5 output

    //for D6 AND gate (S2, S1, S0n)
    andGate and13(S2, S1, E13);
    andGate and14(S0n, I6, E14);
    andGate and_D6(E13, E14, D6); // D6 output

    //for D7 AND gate (S2, S1, S0)
    andGate and15(S2, S1, E15);
    andGate and16(S0, I7, D7); // D7 output

    // OR gate to combine all AND outputs
    wire OR1, OR2, OR3, OR4, ORFinal1, ORFinal2; // Additional intermediate wires

    orGate_df or1(D0, D1, OR1);
    orGate_df or2(D2, D3, OR2);
    orGate_df or3(D4, D5, OR3);
    orGate_df or4(D6, D7, OR4);
    
    orGate_df orFinal1(OR1, OR2, ORFinal1); 
    orGate_df orFinal2(OR3, OR4, ORFinal2);
    
    orGate_df finalOr(ORFinal1, ORFinal2, Y);  // Finally assign to Y

endmodule

mux8x1_bh.v
module mux8x1_bh(input I0,I1,I2,I3,I4,I5,I6,I7,input S0,S1,S2, output reg Y);
    always @(*) begin
        if (S2 == 0 && S1 == 0 && S0 == 0)
            Y = I0;    // Select I0 when S2 S1 S0 = 000
        else if (S2 == 0 && S1 == 0 && S0 == 1)
            Y = I1;    // Select I1 when S2 S1 S0 = 001
        else if (S2 == 0 && S1 == 1 && S0 == 0)
            Y = I2;    // Select I2 when S2 S1 S0 = 010
        else if (S2 == 0 && S1 == 1 && S0 == 1)
            Y = I3;    // Select I3 when S2 S1 S0 = 011
        else if (S2 == 1 && S1 == 0 && S0 == 0)
            Y = I4;    // Select I4 when S2 S1 S0 = 100
        else if (S2 == 1 && S1 == 0 && S0 == 1)
            Y = I5;    // Select I5 when S2 S1 S0 = 101
        else if (S2 == 1 && S1 == 1 && S0 == 0)
            Y = I6;    // Select I6 when S2 S1 S0 = 110
        else if (S2 == 1 && S1 == 1 && S0 == 1)
            Y = I7;    // Select I7 when S2 S1 S0 = 111
        else
            Y = 1'b0;  // Default case, though not expected
    end
endmodule

// ? Always block to model the behavior of the 8:1 multiplexer using case statement
//     always @(*) begin
//         case ({S2, S1, S0})      // Concatenate the select signals into one value
//             3'b000: Y = I0;      // If select lines are 000, choose I0
//             3'b001: Y = I1;      // If select lines are 001, choose I1
//             3'b010: Y = I2;      // If select lines are 010, choose I2
//             3'b011: Y = I3;      // If select lines are 011, choose I3
//             3'b100: Y = I4;      // If select lines are 100, choose I4
//             3'b101: Y = I5;      // If select lines are 101, choose I5
//             3'b110: Y = I6;      // If select lines are 110, choose I6
//             3'b111: Y = I7;      // If select lines are 111, choose I7
//             default: Y = 1'b0;   // Default case, although it shouldn't be hit in this design
//         endcase
//     end

mux8x1_df.v
module mux8x1_df(input I0,I1,I2,I3,I4,I5,I6,I7,input S0,S1,S2, output Y);
    assign Y = (~S2 & ~S1 & ~S0 & I0) |
            (~S2 & ~S1 &  S0 & I1) |
            (~S2 &  S1 & ~S0 & I2) |
            (~S2 &  S1 &  S0 & I3) |
            ( S2 & ~S1 & ~S0 & I4) |
            ( S2 & ~S1 &  S0 & I5) |
            ( S2 &  S1 & ~S0 & I6) |
            ( S2 &  S1 &  S0 & I7);
endmodule

mux8x1_tb.v
`include "mux8x1_df.v"
`include "mux8x1_bh.v"
`include "mux8x1_st.v"
module mux8x1_tb;
    reg s0,s1,s2; // selectors
    reg i0,i1,i2,i3,i4,i5,i6,i7; // inputs
    wire y_df, y_bh, y_st; //outputs

    initial begin
        $dumpfile("mux8x1.vcd");
        $dumpvars(0, mux8x1_tb);
        $monitor ("S2 S1 S0 = %b%b%b, y_df = %b, y_bh = %b, y_st = %b",
        s2, s1, s0, y_df, y_bh, y_st);

    // Set input values: alternating 1's and 0's for simplicity
    i0 = 0; i1 = 1; i2 = 0; i3 = 1;
    i4 = 0; i5 = 1; i6 = 0; i7 = 1;
    // Test cases
    s2 = 0; s1 = 0; s0 = 0; #10; // Select I0
    s2 = 0; s1 = 0; s0 = 1; #10; // Select I1
    s2 = 0; s1 = 1; s0 = 0; #10; // Select I2
    s2 = 0; s1 = 1; s0 = 1; #10; // Select I3
    s2 = 1; s1 = 0; s0 = 0; #10; // Select I4
    s2 = 1; s1 = 0; s0 = 1; #10; // Select I5
    s2 = 1; s1 = 1; s0 = 0; #10; // Select I6
    s2 = 1; s1 = 1; s0 = 1; #10; // Select I7
    end


    //Instantiate mux8x1_df 
    mux8x1_df m8x1_df(
        .I0(i0), .I1(i1), .I2(i2), .I3(i3), 
        .I4(i4), .I5(i5), .I6(i6), .I7(i7),
        .S0(s0), .S1(s1), .S2(s2), 
        .Y(y_df)
    );
    //Instantiate mux8x1_df
    mux8x1_bh m8x1_bh(
        .S0(s0), .S1(s1), .S2(s2), 
        .I0(i0), .I1(i1), .I2(i2), .I3(i3), 
        .I4(i4), .I5(i5), .I6(i6), .I7(i7), 
        .Y(y_bh)
    );
    // Instantiate mux8x1_st
    mux8x1_st m8x1_st(
        .S0(s0), .S1(s1), .S2(s2), 
        .I0(i0), .I1(i1), .I2(i2), .I3(i3), 
        .I4(i4), .I5(i5), .I6(i6), .I7(i7), 
        .Y(y_st)
    );


endmodule

mux8x1.vcd
$date
	Wed Oct 09 02:04:33 2024
$end
$version
	Icarus Verilog
$end
$timescale
	1s
$end
$scope module mux8x1_tb $end
$var wire 1 ! y_st $end
$var wire 1 " y_df $end
$var wire 1 # y_bh $end
$var reg 1 $ i0 $end
$var reg 1 % i1 $end
$var reg 1 & i2 $end
$var reg 1 ' i3 $end
$var reg 1 ( i4 $end
$var reg 1 ) i5 $end
$var reg 1 * i6 $end
$var reg 1 + i7 $end
$var reg 1 , s0 $end
$var reg 1 - s1 $end
$var reg 1 . s2 $end
$scope module m8x1_bh $end
$var wire 1 $ I0 $end
$var wire 1 % I1 $end
$var wire 1 & I2 $end
$var wire 1 ' I3 $end
$var wire 1 ( I4 $end
$var wire 1 ) I5 $end
$var wire 1 * I6 $end
$var wire 1 + I7 $end
$var wire 1 , S0 $end
$var wire 1 - S1 $end
$var wire 1 . S2 $end
$var reg 1 # Y $end
$upscope $end
$scope module m8x1_df $end
$var wire 1 $ I0 $end
$var wire 1 % I1 $end
$var wire 1 & I2 $end
$var wire 1 ' I3 $end
$var wire 1 ( I4 $end
$var wire 1 ) I5 $end
$var wire 1 * I6 $end
$var wire 1 + I7 $end
$var wire 1 , S0 $end
$var wire 1 - S1 $end
$var wire 1 . S2 $end
$var wire 1 " Y $end
$upscope $end
$scope module m8x1_st $end
$var wire 1 $ I0 $end
$var wire 1 % I1 $end
$var wire 1 & I2 $end
$var wire 1 ' I3 $end
$var wire 1 ( I4 $end
$var wire 1 ) I5 $end
$var wire 1 * I6 $end
$var wire 1 + I7 $end
$var wire 1 , S0 $end
$var wire 1 - S1 $end
$var wire 1 . S2 $end
$var wire 1 ! Y $end
$var wire 1 / S2n $end
$var wire 1 0 S1n $end
$var wire 1 1 S0n $end
$var wire 1 2 ORFinal2 $end
$var wire 1 3 ORFinal1 $end
$var wire 1 4 OR4 $end
$var wire 1 5 OR3 $end
$var wire 1 6 OR2 $end
$var wire 1 7 OR1 $end
$var wire 1 8 E9 $end
$var wire 1 9 E8 $end
$var wire 1 : E7 $end
$var wire 1 ; E6 $end
$var wire 1 < E5 $end
$var wire 1 = E4 $end
$var wire 1 > E3 $end
$var wire 1 ? E2 $end
$var wire 1 @ E15 $end
$var wire 1 A E14 $end
$var wire 1 B E13 $end
$var wire 1 C E12 $end
$var wire 1 D E11 $end
$var wire 1 E E10 $end
$var wire 1 F E1 $end
$var wire 1 G D7 $end
$var wire 1 H D6 $end
$var wire 1 I D5 $end
$var wire 1 J D4 $end
$var wire 1 K D3 $end
$var wire 1 L D2 $end
$var wire 1 M D1 $end
$var wire 1 N D0 $end
$scope module and1 $end
$var wire 1 F c $end
$var wire 1 0 b $end
$var wire 1 / a $end
$upscope $end
$scope module and10 $end
$var wire 1 ( b $end
$var wire 1 E c $end
$var wire 1 1 a $end
$upscope $end
$scope module and11 $end
$var wire 1 . a $end
$var wire 1 D c $end
$var wire 1 0 b $end
$upscope $end
$scope module and12 $end
$var wire 1 , a $end
$var wire 1 ) b $end
$var wire 1 C c $end
$upscope $end
$scope module and13 $end
$var wire 1 . a $end
$var wire 1 - b $end
$var wire 1 B c $end
$upscope $end
$scope module and14 $end
$var wire 1 * b $end
$var wire 1 A c $end
$var wire 1 1 a $end
$upscope $end
$scope module and15 $end
$var wire 1 . a $end
$var wire 1 - b $end
$var wire 1 @ c $end
$upscope $end
$scope module and16 $end
$var wire 1 , a $end
$var wire 1 + b $end
$var wire 1 G c $end
$upscope $end
$scope module and2 $end
$var wire 1 $ b $end
$var wire 1 ? c $end
$var wire 1 1 a $end
$upscope $end
$scope module and3 $end
$var wire 1 > c $end
$var wire 1 0 b $end
$var wire 1 / a $end
$upscope $end
$scope module and4 $end
$var wire 1 , a $end
$var wire 1 % b $end
$var wire 1 = c $end
$upscope $end
$scope module and5 $end
$var wire 1 - b $end
$var wire 1 < c $end
$var wire 1 / a $end
$upscope $end
$scope module and6 $end
$var wire 1 & b $end
$var wire 1 ; c $end
$var wire 1 1 a $end
$upscope $end
$scope module and7 $end
$var wire 1 - b $end
$var wire 1 : c $end
$var wire 1 / a $end
$upscope $end
$scope module and8 $end
$var wire 1 , a $end
$var wire 1 ' b $end
$var wire 1 9 c $end
$upscope $end
$scope module and9 $end
$var wire 1 . a $end
$var wire 1 8 c $end
$var wire 1 0 b $end
$upscope $end
$scope module and_D0 $end
$var wire 1 F a $end
$var wire 1 ? b $end
$var wire 1 N c $end
$upscope $end
$scope module and_D1 $end
$var wire 1 > a $end
$var wire 1 = b $end
$var wire 1 M c $end
$upscope $end
$scope module and_D2 $end
$var wire 1 < a $end
$var wire 1 ; b $end
$var wire 1 L c $end
$upscope $end
$scope module and_D3 $end
$var wire 1 : a $end
$var wire 1 9 b $end
$var wire 1 K c $end
$upscope $end
$scope module and_D4 $end
$var wire 1 8 a $end
$var wire 1 E b $end
$var wire 1 J c $end
$upscope $end
$scope module and_D5 $end
$var wire 1 D a $end
$var wire 1 C b $end
$var wire 1 I c $end
$upscope $end
$scope module and_D6 $end
$var wire 1 B a $end
$var wire 1 A b $end
$var wire 1 H c $end
$upscope $end
$scope module finalOr $end
$var wire 1 ! c $end
$var wire 1 2 b $end
$var wire 1 3 a $end
$upscope $end
$scope module not0 $end
$var wire 1 , a $end
$var wire 1 1 b $end
$upscope $end
$scope module not1 $end
$var wire 1 - a $end
$var wire 1 0 b $end
$upscope $end
$scope module not2 $end
$var wire 1 . a $end
$var wire 1 / b $end
$upscope $end
$scope module or1 $end
$var wire 1 N a $end
$var wire 1 M b $end
$var wire 1 7 c $end
$upscope $end
$scope module or2 $end
$var wire 1 L a $end
$var wire 1 K b $end
$var wire 1 6 c $end
$upscope $end
$scope module or3 $end
$var wire 1 J a $end
$var wire 1 I b $end
$var wire 1 5 c $end
$upscope $end
$scope module or4 $end
$var wire 1 H a $end
$var wire 1 G b $end
$var wire 1 4 c $end
$upscope $end
$scope module orFinal1 $end
$var wire 1 7 a $end
$var wire 1 6 b $end
$var wire 1 3 c $end
$upscope $end
$scope module orFinal2 $end
$var wire 1 5 a $end
$var wire 1 4 b $end
$var wire 1 2 c $end
$upscope $end
$upscope $end
$upscope $end
$enddefinitions $end
$comment Show the parameter values. $end
$dumpall
$end
#0
$dumpvars
0N
0M
0L
0K
0J
0I
0H
0G
1F
0E
0D
0C
0B
0A
0@
0?
1>
0=
0<
0;
0:
09
08
07
06
05
04
03
02
11
10
1/
0.
0-
0,
1+
0*
1)
0(
1'
0&
1%
0$
0#
0"
0!
$end
#10
1"
1!
13
12
17
14
1M
1#
1C
1G
1=
19
01
1,
#20
0"
0!
03
02
07
04
0M
0C
0G
0=
09
0#
1<
1:
0>
0F
11
0,
00
1-
#30
1"
1!
13
12
16
14
1K
1#
1C
1G
1=
19
01
1,
#40
0"
0!
03
02
06
04
0K
0C
0G
0=
09
0#
1D
18
0:
0<
11
0,
10
0-
0/
1.
#50
1"
1!
15
12
1I
14
1#
1C
1G
1=
19
01
1,
#60
0"
0!
02
05
04
0I
0C
0G
0=
09
0#
1B
1@
08
0D
11
0,
00
1-
#70
1!
1"
12
14
1#
1C
1G
1=
19
01
1,
