problem1A.v
module problem1A (input W, X,Y,Z, output E,F);
    assign E = W | (X&Y) | ((~X)&Z);
    assign F = ((~X)&Y) | (X&(~Y)&Z);
endmodule

problem1A_tb.v
`include "problem1A.v"

module problem1A_tb;
    reg W,X,Y,Z;
    wire E,F;
    
    initial begin
        $dumpfile("problem1A.vcd");
        $dumpvars(0, problem1A_tb);
        $monitor("W=%b | X=%b | Y=%b | Z=%b || E=%b | F=%b", W, X, Y, Z, E, F);
        
        W=0; X=0; Y=0; Z=0; #5; //0
        W=0; X=0; Y=0; Z=1; #5; //1
        W=0; X=0; Y=1; Z=0; #5; //2
        W=0; X=0; Y=1; Z=1; #5; //3
        W=0; X=1; Y=0; Z=0; #5; //4
        W=0; X=1; Y=0; Z=1; #5; //5
        W=0; X=1; Y=1; Z=0; #5; //6
        W=0; X=1; Y=1; Z=1; #5; //7
        W=1; X=0; Y=0; Z=0; #5; //8
        W=1; X=0; Y=0; Z=1; #5; //9
        W=1; X=0; Y=1; Z=0; #5; //10
        W=1; X=0; Y=1; Z=1; #5; //11
        W=1; X=1; Y=0; Z=0; #5; //12
        W=1; X=1; Y=0; Z=1; #5; //13
        W=1; X=1; Y=1; Z=0; #5; //14
        W=1; X=1; Y=1; Z=1; #5; //15
        $finish;
    end

    // instantiate module
problem1A solve(
    .W(W),
    .X(X),
    .Y(Y),
    .Z(Z),
    .E(E),
    .F(F)
);

endmodule

problem1A.vcd
$date
	Wed Nov 06 17:16:58 2024
$end
$version
	Icarus Verilog
$end
$timescale
	1s
$end
$scope module problem1A_tb $end
$var wire 1 ! F $end
$var wire 1 " E $end
$var reg 1 # W $end
$var reg 1 $ X $end
$var reg 1 % Y $end
$var reg 1 & Z $end
$scope module solve $end
$var wire 1 " E $end
$var wire 1 ! F $end
$var wire 1 # W $end
$var wire 1 $ X $end
$var wire 1 % Y $end
$var wire 1 & Z $end
$upscope $end
$upscope $end
$enddefinitions $end
$comment Show the parameter values. $end
$dumpall
$end
#0
$dumpvars
0&
0%
0$
0#
0"
0!
$end
#5
1"
1&
#10
0"
1!
0&
1%
#15
1"
1&
#20
0"
0!
0&
0%
1$
#25
1!
1&
#30
1"
0!
0&
1%
#35
1&
#40
0&
0%
0$
1#
#45
1&
#50
1!
0&
1%
#55
1&
#60
0!
0&
0%
1$
#65
1!
1&
#70
0!
0&
1%
#75
1&
